xcmocean/__init__.py
xcmocean/accessor.py
xcmocean/options.py
xcmocean-0.3.2.dist-info/LICENSE
xcmocean-0.3.2.dist-info/METADATA
xcmocean-0.3.2.dist-info/WHEEL
xcmocean-0.3.2.dist-info/top_level.txt
xcmocean-0.3.2.dist-info/RECORD
