Metadata-Version: 2.1
Name: xcmocean
Version: 0.3.2
Summary: Opinionated xarray accessor for choosing colormaps
Home-page: https://github.com/kthyng/xcmocean
Author: Kristen Thyng
License: MIT
Requires-Python: >=3.6
License-File: LICENSE
Requires-Dist: xarray
Requires-Dist: cmocean
